schemon_python_logger/__init__.py
schemon_python_logger/decorator.py
schemon_python_logger/logger.py
schemon_python_logger/print.py
schemon_python_logger-0.0.14.dist-info/LICENSE
schemon_python_logger-0.0.14.dist-info/METADATA
schemon_python_logger-0.0.14.dist-info/WHEEL
schemon_python_logger-0.0.14.dist-info/top_level.txt
schemon_python_logger-0.0.14.dist-info/RECORD
