Metadata-Version: 2.1
Name: schemon-python-logger
Version: 0.0.14
Summary: UNKNOWN
Home-page: UNKNOWN
License: Apache License 2.0
Platform: UNKNOWN
Requires-Python: >=3.9
Requires-Dist: pyspark==3.5.0
Requires-Dist: tabulate==0.9.0
